{"Version de Documento":"0.1","Version del Juego":"1.1.1","Version de Parametros":"0.1","Players":[{"ID":"1576190828","Nivel":"1","Nombre":"Carlos","Edad":"12","GameSessions":[{"TimeStamp":"1545438204","MiniGameSessions":[{"ID":"5","TimeStamp":"1545438204","ActivitySessions":[{"ID":"2","TimeStampStart":"1545438204","TimeStampEnd":"1545438207","TimeToFirstEvent":"1545438205","LevelOfAccomplishment":1,"EstadoInicialSockets":"0,1884.083,412.129;","EstadoInicialObjetos":"0,0.2754509,0.1974896,2;1,0.3367507,0.1974896,3;2,0.3980505,0.1974896,4;3,0.4593503,0.1974896,5;4,0.5206498,0.1974896,6;5,0.5819495,0.1974896,7;6,0.6432493,0.1974896,8;7,0.7045491,0.1974896,9;","EstadoFinal":"0,5,5;","ActionEvents":[{"TimeStamp":"1545438205","type":"touch","coordenadaInicioX":"0.4505703","coordenadaInicioY":"0.1891892","coordenadaFinX":"","coordenadaFinY":"","CoordinatesStart":"(0.5, 0.2)","CoordinatesEnd":"","ObjectInteractedID":"Mesa","ObjectID":"Mesa"},{"TimeStamp":"1545438205","type":"DAndD","coordenadaInicioX":"0.4505703","coordenadaInicioY":"0.1891892","coordenadaFinX":"0.5304183","coordenadaFinY":"0.6756757","CoordinatesStart":"(0.5, 0.2)","CoordinatesEnd":"(0.5, 0.7)","ObjectInteractedID":"5","ObjectID":"3"},{"TimeStamp":"1545438206","type":"touch","coordenadaInicioX":"0.865019","coordenadaInicioY":"0.1554054","coordenadaFinX":"","coordenadaFinY":"","CoordinatesStart":"(0.9, 0.2)","CoordinatesEnd":"","ObjectInteractedID":"Mesa","ObjectID":"Mesa"},{"TimeStamp":"1545438207","type":"touch","coordenadaInicioX":"0.865019","coordenadaInicioY":"0.1554054","coordenadaFinX":"","coordenadaFinY":"","CoordinatesStart":"(0.9, 0.2)","CoordinatesEnd":"","ObjectInteractedID":"Mesa","ObjectID":"Mesa"}]}]}]}]}]}