{"Version de Documento":"0.1","Version del Juego":"1.1.1","Version de Parametros":"0.1","Players":[{"ID":"-1586996920","Nivel":"-1","Nombre":"Cristina","Edad":"9","GameSessions":[{"TimeStamp":"1548434197","MiniGameSessions":[{"ID":"0","TimeStamp":"1548434197","ActivitySessions":[{"ID":"1","TimeStampStart":"1548434197","TimeStampEnd":"1548434238","TimeToFirstEvent":"1548434200","LevelOfAccomplishment":2,"EstadoInicialSockets":"0,0.2743682,0.5673929,0;1,0.5,0.5673929,1;2,0.7256318,0.5673929,2;","EstadoInicialObjetos":"0,0.5465174,0.1915907,0;1,0.2674133,0.1915907,1;2,0.4534827,0.1915907,2;3,0.7152652,0.3376733,0;4,0.543053,0.3376733,1;5,0.3604479,0.1915907,2;6,0.3708409,0.3376733,0;7,0.2847348,0.3376733,1;8,0.7325867,0.1915907,2;9,0.6291591,0.3376733,0;10,0.456947,0.3376733,1;11,0.6395521,0.1915907,2;","EstadoFinal":"0,0,0,0,0;1,1,1,1,1;2,2,2,2,2;","ActionEvents":[{"TimeStamp":"1548434199","type":"touch","coordenadaInicioX":"0.3604167","coordenadaInicioY":"0.2775","coordenadaFinX":"","coordenadaFinY":"","CoordinatesStart":"(0.4, 0.3)","CoordinatesEnd":"","ObjectInteractedID":"Piso","ObjectID":"Piso"},{"TimeStamp":"1548434200","type":"DAndD","coordenadaInicioX":"0.3604167","coordenadaInicioY":"0.2775","coordenadaFinX":"0.2682292","coordenadaFinY":"0.5720834","CoordinatesStart":"(0.4, 0.3)","CoordinatesEnd":"(0.3, 0.6)","ObjectInteractedID":"0","ObjectID":"0"},{"TimeStamp":"1548434205","type":"touch","coordenadaInicioX":"0.6859375","coordenadaInicioY":"0.27","coordenadaFinX":"","coordenadaFinY":"","CoordinatesStart":"(0.7, 0.3)","CoordinatesEnd":"","ObjectInteractedID":"Piso","ObjectID":"Piso"},{"TimeStamp":"1548434206","type":"DAndD","coordenadaInicioX":"0.6859375","coordenadaInicioY":"0.27","coordenadaFinX":"0.2804688","coordenadaFinY":"0.59625","CoordinatesStart":"(0.7, 0.3)","CoordinatesEnd":"(0.3, 0.6)","ObjectInteractedID":"0","ObjectID":"0"},{"TimeStamp":"1548434206","type":"touch","coordenadaInicioX":"0.559375","coordenadaInicioY":"0.1433333","coordenadaFinX":"","coordenadaFinY":"","CoordinatesStart":"(0.6, 0.1)","CoordinatesEnd":"","ObjectInteractedID":"Piso","ObjectID":"Piso"},{"TimeStamp":"1548434207","type":"DAndD","coordenadaInicioX":"0.559375","coordenadaInicioY":"0.1433333","coordenadaFinX":"0.2742187","coordenadaFinY":"0.5858333","CoordinatesStart":"(0.6, 0.1)","CoordinatesEnd":"(0.3, 0.6)","ObjectInteractedID":"0","ObjectID":"0"},{"TimeStamp":"1548434207","type":"touch","coordenadaInicioX":"0.6322917","coordenadaInicioY":"0.2675","coordenadaFinX":"","coordenadaFinY":"","CoordinatesStart":"(0.6, 0.3)","CoordinatesEnd":"","ObjectInteractedID":"Piso","ObjectID":"Piso"},{"TimeStamp":"1548434208","type":"DAndD","coordenadaInicioX":"0.6322917","coordenadaInicioY":"0.2675","coordenadaFinX":"0.2651042","coordenadaFinY":"0.6033334","CoordinatesStart":"(0.6, 0.3)","CoordinatesEnd":"(0.3, 0.6)","ObjectInteractedID":"0","ObjectID":"0"},{"TimeStamp":"1548434209","type":"touch","coordenadaInicioX":"0.3197917","coordenadaInicioY":"0.6658334","coordenadaFinX":"","coordenadaFinY":"","CoordinatesStart":"(0.3, 0.7)","CoordinatesEnd":"","ObjectInteractedID":"0","ObjectID":"0"},{"TimeStamp":"1548434210","type":"DAndD","coordenadaInicioX":"0.3197917","coordenadaInicioY":"0.6658334","coordenadaFinX":"0.2844905","coordenadaFinY":"0.6216667","CoordinatesStart":"(0.3, 0.7)","CoordinatesEnd":"(0.3, 0.6)","ObjectInteractedID":"0","ObjectID":"0"},{"TimeStamp":"1548434213","type":"touch","coordenadaInicioX":"0.2546875","coordenadaInicioY":"0.3783333","coordenadaFinX":"","coordenadaFinY":"","CoordinatesStart":"(0.3, 0.4)","CoordinatesEnd":"","ObjectInteractedID":"Piso","ObjectID":"Piso"},{"TimeStamp":"1548434214","type":"DAndD","coordenadaInicioX":"0.2546875","coordenadaInicioY":"0.3783333","coordenadaFinX":"0.2453125","coordenadaFinY":"0.6095833","CoordinatesStart":"(0.3, 0.4)","CoordinatesEnd":"(0.2, 0.6)","ObjectInteractedID":"0","ObjectID":"0"},{"TimeStamp":"1548434214","type":"touch","coordenadaInicioX":"0.3854167","coordenadaInicioY":"0.7066666","coordenadaFinX":"","coordenadaFinY":"","CoordinatesStart":"(0.4, 0.7)","CoordinatesEnd":"","ObjectInteractedID":"Piso","ObjectID":"Piso"},{"TimeStamp":"1548434215","type":"DAndD","coordenadaInicioX":"0.3854167","coordenadaInicioY":"0.7066666","coordenadaFinX":"0.3067708","coordenadaFinY":"0.595","CoordinatesStart":"(0.4, 0.7)","CoordinatesEnd":"(0.3, 0.6)","ObjectInteractedID":"0","ObjectID":"0"},{"TimeStamp":"1548434216","type":"touch","coordenadaInicioX":"0.2911458","coordenadaInicioY":"0.2833333","coordenadaFinX":"","coordenadaFinY":"","CoordinatesStart":"(0.3, 0.3)","CoordinatesEnd":"","ObjectInteractedID":"Piso","ObjectID":"Piso"},{"TimeStamp":"1548434216","type":"DAndD","coordenadaInicioX":"0.2911458","coordenadaInicioY":"0.2833333","coordenadaFinX":"0.5036458","coordenadaFinY":"0.5866666","CoordinatesStart":"(0.3, 0.3)","CoordinatesEnd":"(0.5, 0.6)","ObjectInteractedID":"1","ObjectID":"1"},{"TimeStamp":"1548434217","type":"touch","coordenadaInicioX":"0.3088542","coordenadaInicioY":"0.1658333","coordenadaFinX":"","coordenadaFinY":"","CoordinatesStart":"(0.3, 0.2)","CoordinatesEnd":"","ObjectInteractedID":"Piso","ObjectID":"Piso"},{"TimeStamp":"1548434217","type":"DAndD","coordenadaInicioX":"0.3088542","coordenadaInicioY":"0.1658333","coordenadaFinX":"0.5065104","coordenadaFinY":"0.6133333","CoordinatesStart":"(0.3, 0.2)","CoordinatesEnd":"(0.5, 0.6)","ObjectInteractedID":"1","ObjectID":"1"},{"TimeStamp":"1548434223","type":"touch","coordenadaInicioX":"0.5557292","coordenadaInicioY":"0.2383333","coordenadaFinX":"","coordenadaFinY":"","CoordinatesStart":"(0.6, 0.2)","CoordinatesEnd":"","ObjectInteractedID":"Piso","ObjectID":"Piso"},{"TimeStamp":"1548434224","type":"DAndD","coordenadaInicioX":"0.5557292","coordenadaInicioY":"0.2383333","coordenadaFinX":"0.5109375","coordenadaFinY":"0.6566667","CoordinatesStart":"(0.6, 0.2)","CoordinatesEnd":"(0.5, 0.7)","ObjectInteractedID":"1","ObjectID":"1"},{"TimeStamp":"1548434225","type":"touch","coordenadaInicioX":"0.4640625","coordenadaInicioY":"0.27","coordenadaFinX":"","coordenadaFinY":"","CoordinatesStart":"(0.5, 0.3)","CoordinatesEnd":"","ObjectInteractedID":"Piso","ObjectID":"Piso"},{"TimeStamp":"1548434226","type":"DAndD","coordenadaInicioX":"0.4640625","coordenadaInicioY":"0.27","coordenadaFinX":"0.4626434","coordenadaFinY":"0.6091667","CoordinatesStart":"(0.5, 0.3)","CoordinatesEnd":"(0.5, 0.6)","ObjectInteractedID":"1","ObjectID":"1"},{"TimeStamp":"1548434226","type":"touch","coordenadaInicioX":"0.5234375","coordenadaInicioY":"0.5833333","coordenadaFinX":"","coordenadaFinY":"","CoordinatesStart":"(0.5, 0.6)","CoordinatesEnd":"","ObjectInteractedID":"1","ObjectID":"1"},{"TimeStamp":"1548434227","type":"DAndD","coordenadaInicioX":"0.5234375","coordenadaInicioY":"0.5833333","coordenadaFinX":"0.5604166","coordenadaFinY":"0.6058334","CoordinatesStart":"(0.5, 0.6)","CoordinatesEnd":"(0.6, 0.6)","ObjectInteractedID":"1","ObjectID":"1"},{"TimeStamp":"1548434228","type":"touch","coordenadaInicioX":"0.4625","coordenadaInicioY":"0.1375","coordenadaFinX":"","coordenadaFinY":"","CoordinatesStart":"(0.5, 0.1)","CoordinatesEnd":"","ObjectInteractedID":"Piso","ObjectID":"Piso"},{"TimeStamp":"1548434229","type":"DAndD","coordenadaInicioX":"0.4625","coordenadaInicioY":"0.1375","coordenadaFinX":"0.7307292","coordenadaFinY":"0.6312878","CoordinatesStart":"(0.5, 0.1)","CoordinatesEnd":"(0.7, 0.6)","ObjectInteractedID":"2","ObjectID":"2"},{"TimeStamp":"1548434230","type":"touch","coordenadaInicioX":"0.3572917","coordenadaInicioY":"0.1283333","coordenadaFinX":"","coordenadaFinY":"","CoordinatesStart":"(0.4, 0.1)","CoordinatesEnd":"","ObjectInteractedID":"Piso","ObjectID":"Piso"},{"TimeStamp":"1548434231","type":"DAndD","coordenadaInicioX":"0.3572917","coordenadaInicioY":"0.1283333","coordenadaFinX":"0.7291667","coordenadaFinY":"0.6291667","CoordinatesStart":"(0.4, 0.1)","CoordinatesEnd":"(0.7, 0.6)","ObjectInteractedID":"2","ObjectID":"2"},{"TimeStamp":"1548434232","type":"touch","coordenadaInicioX":"0.6421875","coordenadaInicioY":"0.1466667","coordenadaFinX":"","coordenadaFinY":"","CoordinatesStart":"(0.6, 0.1)","CoordinatesEnd":"","ObjectInteractedID":"Piso","ObjectID":"Piso"},{"TimeStamp":"1548434233","type":"DAndD","coordenadaInicioX":"0.6421875","coordenadaInicioY":"0.1466667","coordenadaFinX":"0.7463542","coordenadaFinY":"0.6341667","CoordinatesStart":"(0.6, 0.1)","CoordinatesEnd":"(0.7, 0.6)","ObjectInteractedID":"2","ObjectID":"2"},{"TimeStamp":"1548434233","type":"touch","coordenadaInicioX":"0.715625","coordenadaInicioY":"0.09","coordenadaFinX":"","coordenadaFinY":"","CoordinatesStart":"(0.7, 0.1)","CoordinatesEnd":"","ObjectInteractedID":"Piso","ObjectID":"Piso"},{"TimeStamp":"1548434235","type":"DAndD","coordenadaInicioX":"0.715625","coordenadaInicioY":"0.09","coordenadaFinX":"0.7264489","coordenadaFinY":"0.6171364","CoordinatesStart":"(0.7, 0.1)","CoordinatesEnd":"(0.7, 0.6)","ObjectInteractedID":"2","ObjectID":"2"},{"TimeStamp":"1548434238","type":"touch","coordenadaInicioX":"0.94375","coordenadaInicioY":"0.08916666","coordenadaFinX":"","coordenadaFinY":"","CoordinatesStart":"(0.9, 0.1)","CoordinatesEnd":"","ObjectInteractedID":"Piso","ObjectID":"Piso"}]}]}]}]}]}