{"Version de Documento":"0.1","Version del Juego":"1.1.1","Version de Parametros":"0.1","Players":[{"ID":"839895537","Nivel":"1","Nombre":"Pruenaunoj","Edad":"10","GameSessions":[{"TimeStamp":"1553909752","MiniGameSessions":[{"ID":"1","TimeStamp":"1553909752","ActivitySessions":[{"ID":"0","TimeStampStart":"1553909752","TimeStampEnd":"1553909754","TimeToFirstEvent":"1553909754","LevelOfAccomplishment":1,"EstadoInicialSockets":"0,0.7430785,0.4862798;","EstadoInicialObjetos":"0,0.3728373,0.5047014,0;1,0.1642421,0.5047092,1;2,0.531679,0.5046955,2;","EstadoFinal":"0,2,2","ActionEvents":[{"TimeStamp":"1553909753","type":"touch","coordenadaInicioX":"0.5273632","coordenadaInicioY":"0.5222222","coordenadaFinX":"","coordenadaFinY":"","CoordinatesStart":"(0.5, 0.5)","CoordinatesEnd":"","ObjectInteractedID":"Meson-2","ObjectID":"Meson-2"},{"TimeStamp":"1553909754","type":"DAndD","coordenadaInicioX":"0.5273632","coordenadaInicioY":"0.5222222","coordenadaFinX":"0.7562189","coordenadaFinY":"0.5311111","CoordinatesStart":"(0.5, 0.5)","CoordinatesEnd":"(0.8, 0.5)","ObjectInteractedID":"2","ObjectID":"2"},{"TimeStamp":"1553909754","type":"touch","coordenadaInicioX":"0.8669154","coordenadaInicioY":"0.09111111","coordenadaFinX":"","coordenadaFinY":"","CoordinatesStart":"(0.9, 0.1)","CoordinatesEnd":"","ObjectInteractedID":"Meson-2","ObjectID":"Meson-2"},{"TimeStamp":"1553909754","type":"touch","coordenadaInicioX":"0.8681592","coordenadaInicioY":"0.08888889","coordenadaFinX":"","coordenadaFinY":"","CoordinatesStart":"(0.9, 0.1)","CoordinatesEnd":"","ObjectInteractedID":"Meson-2","ObjectID":"Meson-2"}]}]}]}]}]}