{"Version de Documento":"0.1","Version del Juego":"1.1.1","Version de Parametros":"0.1","Players":[{"ID":"1576168587","Nivel":"1","Nombre":"Pruebaunom","Edad":"13","GameSessions":[{"TimeStamp":"1553913559","MiniGameSessions":[{"ID":"5","TimeStamp":"1553913559","ActivitySessions":[{"ID":"2","TimeStampStart":"1553913559","TimeStampEnd":"1553913561","TimeToFirstEvent":"1553913560","LevelOfAccomplishment":1,"EstadoInicialSockets":"0,5909.839,1287.903;","EstadoInicialObjetos":"0,0.2754509,0.196355,2;1,0.3367507,0.196355,3;2,0.3980505,0.196355,4;3,0.4593503,0.196355,5;4,0.5206498,0.196355,6;5,0.5819495,0.196355,7;6,0.6432493,0.196355,8;7,0.7045491,0.196355,9;","EstadoFinal":"0,8,6","ActionEvents":[{"TimeStamp":"1553913560","type":"touch","coordenadaInicioX":"0.6425903","coordenadaInicioY":"0.2133333","coordenadaFinX":"","coordenadaFinY":"","CoordinatesStart":"(0.6, 0.2)","CoordinatesEnd":"","ObjectInteractedID":"Mesa","ObjectID":"Mesa"},{"TimeStamp":"1553913560","type":"DAndD","coordenadaInicioX":"0.6425903","coordenadaInicioY":"0.2133333","coordenadaFinX":"0.5305106","coordenadaFinY":"0.7177778","CoordinatesStart":"(0.6, 0.2)","CoordinatesEnd":"(0.5, 0.7)","ObjectInteractedID":"8","ObjectID":"6"},{"TimeStamp":"1553913560","type":"touch","coordenadaInicioX":"0.9066002","coordenadaInicioY":"0.08666667","coordenadaFinX":"","coordenadaFinY":"","CoordinatesStart":"(0.9, 0.1)","CoordinatesEnd":"","ObjectInteractedID":"Mesa","ObjectID":"Mesa"},{"TimeStamp":"1553913561","type":"touch","coordenadaInicioX":"0.8991283","coordenadaInicioY":"0.07777778","coordenadaFinX":"","coordenadaFinY":"","CoordinatesStart":"(0.9, 0.1)","CoordinatesEnd":"","ObjectInteractedID":"Mesa","ObjectID":"Mesa"},{"TimeStamp":"1553913561","type":"touch","coordenadaInicioX":"0.8816937","coordenadaInicioY":"0.07777778","coordenadaFinX":"","coordenadaFinY":"","CoordinatesStart":"(0.9, 0.1)","CoordinatesEnd":"","ObjectInteractedID":"Mesa","ObjectID":"Mesa"}]}]}]}]}]}